dqcsim_openql_mapper/__init__.py
dqcsim_openql_mapper/test.py
dqcsim_openql_mapper-0.0.3.data/data/bin/dqcsopopenql-mapper
dqcsim_openql_mapper-0.0.3.dist-info/WHEEL
dqcsim_openql_mapper-0.0.3.dist-info/METADATA
dqcsim_openql_mapper-0.0.3.dist-info/top_level.txt
dqcsim_openql_mapper-0.0.3.dist-info/entry_points.txt
dqcsim_openql_mapper-0.0.3.dist-info/RECORD
