Metadata-Version: 2.1
Name: dqcsim-openql-mapper
Version: 0.0.3
Summary: The OpenQL mapper wrapped in a DQCsim operator
Home-page: https://github.com/QE-Lab/dqcsim-openql-mapper
Author: Quantum Computer Architectures, Quantum & Computer Engineering, QuTech, Delft University of Technology
Author-email: 
License: Apache-2.0
Project-URL: Source Code, https://github.com/QE-Lab/dqcsim-openql-mapper
Platform: UNKNOWN
Classifier: License :: OSI Approved :: Apache Software License
Classifier: Operating System :: POSIX :: Linux
Classifier: Programming Language :: C
Classifier: Programming Language :: C++
Classifier: Topic :: Scientific/Engineering
Requires-Dist: dqcsim (>=0.0.13)
